{
  "notes": "RUN139 Darvas Box filter. 10 configs. Baseline PnL=360.55. Best: BASELINE (PnL=360.55, Δ=+0.00)",
  "configs": [
    {
      "label": "BASELINE",
      "total_pnl": 360.5530969929427,
      "portfolio_wr": 39.00211848929798,
      "total_trades": 13689,
      "wins": 5339,
      "losses": 8347,
      "flats": 3,
      "pf": 0.6396310051515515,
      "is_baseline": true,
      "coins": [
        {
          "coin": "DASH",
          "pnl": 51.997306058204,
          "trades": 808,
          "wins": 241,
          "losses": 567,
          "flats": 0,
          "wr": 29.826732673267326,
          "pf": 0.4250440917107583,
          "entries_filtered": 0
        },
        {
          "coin": "UNI",
          "pnl": 27.35291337250743,
          "trades": 768,
          "wins": 292,
          "losses": 476,
          "flats": 0,
          "wr": 38.02083333333333,
          "pf": 0.6134453781512605,
          "entries_filtered": 0
        },
        {
          "coin": "NEAR",
          "pnl": 30.86500339800787,
          "trades": 766,
          "wins": 285,
          "losses": 481,
          "flats": 0,
          "wr": 37.206266318537864,
          "pf": 0.5925155925155925,
          "entries_filtered": 0
        },
        {
          "coin": "ADA",
          "pnl": 22.211602468364646,
          "trades": 772,
          "wins": 306,
          "losses": 465,
          "flats": 1,
          "wr": 39.637305699481864,
          "pf": 0.6580645161290323,
          "entries_filtered": 0
        },
        {
          "coin": "LTC",
          "pnl": 16.48435837958715,
          "trades": 740,
          "wins": 300,
          "losses": 440,
          "flats": 0,
          "wr": 40.54054054054054,
          "pf": 0.6818181818181819,
          "entries_filtered": 0
        },
        {
          "coin": "SHIB",
          "pnl": 17.954362185417963,
          "trades": 769,
          "wins": 291,
          "losses": 478,
          "flats": 0,
          "wr": 37.841352405721715,
          "pf": 0.6087866108786611,
          "entries_filtered": 0
        },
        {
          "coin": "LINK",
          "pnl": 22.66187588531274,
          "trades": 760,
          "wins": 311,
          "losses": 448,
          "flats": 1,
          "wr": 40.921052631578945,
          "pf": 0.6941964285714285,
          "entries_filtered": 0
        },
        {
          "coin": "ETH",
          "pnl": 16.793977165031734,
          "trades": 754,
          "wins": 326,
          "losses": 428,
          "flats": 0,
          "wr": 43.236074270557026,
          "pf": 0.7616822429906542,
          "entries_filtered": 0
        },
        {
          "coin": "DOT",
          "pnl": 23.619087305892123,
          "trades": 766,
          "wins": 299,
          "losses": 467,
          "flats": 0,
          "wr": 39.03394255874674,
          "pf": 0.6402569593147751,
          "entries_filtered": 0
        },
        {
          "coin": "XRP",
          "pnl": 15.86948661675379,
          "trades": 776,
          "wins": 314,
          "losses": 462,
          "flats": 0,
          "wr": 40.4639175257732,
          "pf": 0.6796536796536797,
          "entries_filtered": 0
        },
        {
          "coin": "ATOM",
          "pnl": 18.0399590596505,
          "trades": 756,
          "wins": 280,
          "losses": 476,
          "flats": 0,
          "wr": 37.03703703703704,
          "pf": 0.5882352941176471,
          "entries_filtered": 0
        },
        {
          "coin": "SOL",
          "pnl": 14.975377735368752,
          "trades": 769,
          "wins": 303,
          "losses": 466,
          "flats": 0,
          "wr": 39.401820546163854,
          "pf": 0.6502145922746781,
          "entries_filtered": 0
        },
        {
          "coin": "DOGE",
          "pnl": 15.919499093091929,
          "trades": 764,
          "wins": 304,
          "losses": 460,
          "flats": 0,
          "wr": 39.79057591623037,
          "pf": 0.6608695652173913,
          "entries_filtered": 0
        },
        {
          "coin": "XLM",
          "pnl": 14.645706479929402,
          "trades": 744,
          "wins": 277,
          "losses": 467,
          "flats": 0,
          "wr": 37.23118279569893,
          "pf": 0.5931477516059958,
          "entries_filtered": 0
        },
        {
          "coin": "AVAX",
          "pnl": 18.983326204628,
          "trades": 786,
          "wins": 321,
          "losses": 464,
          "flats": 1,
          "wr": 40.839694656488554,
          "pf": 0.6918103448275862,
          "entries_filtered": 0
        },
        {
          "coin": "ALGO",
          "pnl": 15.585281938097495,
          "trades": 745,
          "wins": 263,
          "losses": 482,
          "flats": 0,
          "wr": 35.30201342281879,
          "pf": 0.545643153526971,
          "entries_filtered": 0
        },
        {
          "coin": "BNB",
          "pnl": 8.090181403174299,
          "trades": 728,
          "wins": 292,
          "losses": 436,
          "flats": 0,
          "wr": 40.10989010989011,
          "pf": 0.6697247706422019,
          "entries_filtered": 0
        },
        {
          "coin": "BTC",
          "pnl": 8.50379224392293,
          "trades": 718,
          "wins": 334,
          "losses": 384,
          "flats": 0,
          "wr": 46.51810584958218,
          "pf": 0.8697916666666666,
          "entries_filtered": 0
        }
      ],
      "entries_filtered_total": 0,
      "filter_rate": 0.0
    },
    {
      "label": "P14_T5",
      "total_pnl": 39.24004183927413,
      "portfolio_wr": 40.01074113856068,
      "total_trades": 1862,
      "wins": 745,
      "losses": 1116,
      "flats": 1,
      "pf": 0.6675627240143369,
      "is_baseline": false,
      "coins": [
        {
          "coin": "DASH",
          "pnl": 3.7352781339998415,
          "trades": 68,
          "wins": 22,
          "losses": 46,
          "flats": 0,
          "wr": 32.35294117647059,
          "pf": 0.4782608695652174,
          "entries_filtered": 1544
        },
        {
          "coin": "UNI",
          "pnl": 3.5199187817408557,
          "trades": 74,
          "wins": 36,
          "losses": 38,
          "flats": 0,
          "wr": 48.64864864864865,
          "pf": 0.9473684210526316,
          "entries_filtered": 1471
        },
        {
          "coin": "NEAR",
          "pnl": 3.695709372990848,
          "trades": 120,
          "wins": 49,
          "losses": 71,
          "flats": 0,
          "wr": 40.833333333333336,
          "pf": 0.6901408450704225,
          "entries_filtered": 1381
        },
        {
          "coin": "ADA",
          "pnl": 1.148024728667636,
          "trades": 54,
          "wins": 21,
          "losses": 33,
          "flats": 0,
          "wr": 38.88888888888889,
          "pf": 0.6363636363636364,
          "entries_filtered": 1569
        },
        {
          "coin": "LTC",
          "pnl": 1.5343875532539073,
          "trades": 64,
          "wins": 31,
          "losses": 33,
          "flats": 0,
          "wr": 48.4375,
          "pf": 0.9393939393939394,
          "entries_filtered": 1512
        },
        {
          "coin": "SHIB",
          "pnl": 3.4826025410254005,
          "trades": 277,
          "wins": 106,
          "losses": 171,
          "flats": 0,
          "wr": 38.26714801444043,
          "pf": 0.6198830409356725,
          "entries_filtered": 1091
        },
        {
          "coin": "LINK",
          "pnl": 3.320393584480101,
          "trades": 156,
          "wins": 63,
          "losses": 92,
          "flats": 1,
          "wr": 40.38461538461539,
          "pf": 0.6847826086956521,
          "entries_filtered": 1285
        },
        {
          "coin": "ETH",
          "pnl": 0.2313374845121814,
          "trades": 25,
          "wins": 9,
          "losses": 16,
          "flats": 0,
          "wr": 36.0,
          "pf": 0.5625,
          "entries_filtered": 1656
        },
        {
          "coin": "DOT",
          "pnl": 1.797686920506635,
          "trades": 123,
          "wins": 41,
          "losses": 82,
          "flats": 0,
          "wr": 33.33333333333333,
          "pf": 0.5,
          "entries_filtered": 1409
        },
        {
          "coin": "XRP",
          "pnl": 0.5726066015187996,
          "trades": 34,
          "wins": 15,
          "losses": 19,
          "flats": 0,
          "wr": 44.11764705882353,
          "pf": 0.7894736842105263,
          "entries_filtered": 1682
        },
        {
          "coin": "ATOM",
          "pnl": 3.2403504804809984,
          "trades": 165,
          "wins": 65,
          "losses": 100,
          "flats": 0,
          "wr": 39.39393939393939,
          "pf": 0.65,
          "entries_filtered": 1301
        },
        {
          "coin": "SOL",
          "pnl": 1.0986279438256759,
          "trades": 30,
          "wins": 17,
          "losses": 13,
          "flats": 0,
          "wr": 56.666666666666664,
          "pf": 1.3076923076923077,
          "entries_filtered": 1675
        },
        {
          "coin": "DOGE",
          "pnl": -0.13617828689586986,
          "trades": 23,
          "wins": 5,
          "losses": 18,
          "flats": 0,
          "wr": 21.73913043478261,
          "pf": 0.2777777777777778,
          "entries_filtered": 1669
        },
        {
          "coin": "XLM",
          "pnl": 2.4616491726331873,
          "trades": 153,
          "wins": 57,
          "losses": 96,
          "flats": 0,
          "wr": 37.254901960784316,
          "pf": 0.59375,
          "entries_filtered": 1376
        },
        {
          "coin": "AVAX",
          "pnl": 3.800006113116723,
          "trades": 160,
          "wins": 72,
          "losses": 88,
          "flats": 0,
          "wr": 45.0,
          "pf": 0.8181818181818181,
          "entries_filtered": 1411
        },
        {
          "coin": "ALGO",
          "pnl": 4.712259188274857,
          "trades": 230,
          "wins": 87,
          "losses": 143,
          "flats": 0,
          "wr": 37.826086956521735,
          "pf": 0.6083916083916084,
          "entries_filtered": 1137
        },
        {
          "coin": "BNB",
          "pnl": 0.4525191135298172,
          "trades": 38,
          "wins": 18,
          "losses": 20,
          "flats": 0,
          "wr": 47.368421052631575,
          "pf": 0.9,
          "entries_filtered": 1659
        },
        {
          "coin": "BTC",
          "pnl": 0.5728624116125332,
          "trades": 68,
          "wins": 31,
          "losses": 37,
          "flats": 0,
          "wr": 45.588235294117645,
          "pf": 0.8378378378378379,
          "entries_filtered": 1552
        }
      ],
      "entries_filtered_total": 26380,
      "filter_rate": 93.40698250832095
    },
    {
      "label": "P14_T10",
      "total_pnl": 39.45675411842802,
      "portfolio_wr": 39.93627190653213,
      "total_trades": 1883,
      "wins": 752,
      "losses": 1130,
      "flats": 1,
      "pf": 0.6654867256637168,
      "is_baseline": false,
      "coins": [
        {
          "coin": "DASH",
          "pnl": 3.7352781339998415,
          "trades": 68,
          "wins": 22,
          "losses": 46,
          "flats": 0,
          "wr": 32.35294117647059,
          "pf": 0.4782608695652174,
          "entries_filtered": 1544
        },
        {
          "coin": "UNI",
          "pnl": 3.5199187817408557,
          "trades": 74,
          "wins": 36,
          "losses": 38,
          "flats": 0,
          "wr": 48.64864864864865,
          "pf": 0.9473684210526316,
          "entries_filtered": 1471
        },
        {
          "coin": "NEAR",
          "pnl": 3.695709372990848,
          "trades": 120,
          "wins": 49,
          "losses": 71,
          "flats": 0,
          "wr": 40.833333333333336,
          "pf": 0.6901408450704225,
          "entries_filtered": 1381
        },
        {
          "coin": "ADA",
          "pnl": 1.148024728667636,
          "trades": 54,
          "wins": 21,
          "losses": 33,
          "flats": 0,
          "wr": 38.88888888888889,
          "pf": 0.6363636363636364,
          "entries_filtered": 1569
        },
        {
          "coin": "LTC",
          "pnl": 1.5343875532539073,
          "trades": 64,
          "wins": 31,
          "losses": 33,
          "flats": 0,
          "wr": 48.4375,
          "pf": 0.9393939393939394,
          "entries_filtered": 1512
        },
        {
          "coin": "SHIB",
          "pnl": 3.4826025410254005,
          "trades": 277,
          "wins": 106,
          "losses": 171,
          "flats": 0,
          "wr": 38.26714801444043,
          "pf": 0.6198830409356725,
          "entries_filtered": 1091
        },
        {
          "coin": "LINK",
          "pnl": 3.320393584480101,
          "trades": 156,
          "wins": 63,
          "losses": 92,
          "flats": 1,
          "wr": 40.38461538461539,
          "pf": 0.6847826086956521,
          "entries_filtered": 1285
        },
        {
          "coin": "ETH",
          "pnl": 0.15319340995873176,
          "trades": 28,
          "wins": 9,
          "losses": 19,
          "flats": 0,
          "wr": 32.142857142857146,
          "pf": 0.4736842105263158,
          "entries_filtered": 1647
        },
        {
          "coin": "DOT",
          "pnl": 1.797686920506635,
          "trades": 123,
          "wins": 41,
          "losses": 82,
          "flats": 0,
          "wr": 33.33333333333333,
          "pf": 0.5,
          "entries_filtered": 1409
        },
        {
          "coin": "XRP",
          "pnl": 0.5424348195383999,
          "trades": 35,
          "wins": 15,
          "losses": 20,
          "flats": 0,
          "wr": 42.857142857142854,
          "pf": 0.7500000000000001,
          "entries_filtered": 1681
        },
        {
          "coin": "ATOM",
          "pnl": 3.2403504804809984,
          "trades": 165,
          "wins": 65,
          "losses": 100,
          "flats": 0,
          "wr": 39.39393939393939,
          "pf": 0.65,
          "entries_filtered": 1301
        },
        {
          "coin": "SOL",
          "pnl": 1.0986279438256759,
          "trades": 30,
          "wins": 17,
          "losses": 13,
          "flats": 0,
          "wr": 56.666666666666664,
          "pf": 1.3076923076923077,
          "entries_filtered": 1675
        },
        {
          "coin": "DOGE",
          "pnl": -0.13617828689586986,
          "trades": 23,
          "wins": 5,
          "losses": 18,
          "flats": 0,
          "wr": 21.73913043478261,
          "pf": 0.2777777777777778,
          "entries_filtered": 1669
        },
        {
          "coin": "XLM",
          "pnl": 2.4616491726331873,
          "trades": 153,
          "wins": 57,
          "losses": 96,
          "flats": 0,
          "wr": 37.254901960784316,
          "pf": 0.59375,
          "entries_filtered": 1376
        },
        {
          "coin": "AVAX",
          "pnl": 3.800006113116723,
          "trades": 160,
          "wins": 72,
          "losses": 88,
          "flats": 0,
          "wr": 45.0,
          "pf": 0.8181818181818181,
          "entries_filtered": 1411
        },
        {
          "coin": "ALGO",
          "pnl": 4.712259188274857,
          "trades": 230,
          "wins": 87,
          "losses": 143,
          "flats": 0,
          "wr": 37.826086956521735,
          "pf": 0.6083916083916084,
          "entries_filtered": 1137
        },
        {
          "coin": "BNB",
          "pnl": 0.6479638020766032,
          "trades": 53,
          "wins": 23,
          "losses": 30,
          "flats": 0,
          "wr": 43.39622641509434,
          "pf": 0.7666666666666666,
          "entries_filtered": 1629
        },
        {
          "coin": "BTC",
          "pnl": 0.7024458587534923,
          "trades": 70,
          "wins": 33,
          "losses": 37,
          "flats": 0,
          "wr": 47.14285714285714,
          "pf": 0.8918918918918919,
          "entries_filtered": 1548
        }
      ],
      "entries_filtered_total": 26336,
      "filter_rate": 93.32719089974839
    },
    {
      "label": "P14_T20",
      "total_pnl": 41.24895474035026,
      "portfolio_wr": 40.03115264797508,
      "total_trades": 1926,
      "wins": 771,
      "losses": 1154,
      "flats": 1,
      "pf": 0.6681109185441942,
      "is_baseline": false,
      "coins": [
        {
          "coin": "DASH",
          "pnl": 4.9721102742616665,
          "trades": 70,
          "wins": 23,
          "losses": 47,
          "flats": 0,
          "wr": 32.857142857142854,
          "pf": 0.48936170212765956,
          "entries_filtered": 1541
        },
        {
          "coin": "UNI",
          "pnl": 3.5199187817408557,
          "trades": 74,
          "wins": 36,
          "losses": 38,
          "flats": 0,
          "wr": 48.64864864864865,
          "pf": 0.9473684210526316,
          "entries_filtered": 1471
        },
        {
          "coin": "NEAR",
          "pnl": 3.695709372990848,
          "trades": 120,
          "wins": 49,
          "losses": 71,
          "flats": 0,
          "wr": 40.833333333333336,
          "pf": 0.6901408450704225,
          "entries_filtered": 1381
        },
        {
          "coin": "ADA",
          "pnl": 1.148024728667636,
          "trades": 54,
          "wins": 21,
          "losses": 33,
          "flats": 0,
          "wr": 38.88888888888889,
          "pf": 0.6363636363636364,
          "entries_filtered": 1569
        },
        {
          "coin": "LTC",
          "pnl": 1.750856805905542,
          "trades": 65,
          "wins": 32,
          "losses": 33,
          "flats": 0,
          "wr": 49.23076923076923,
          "pf": 0.9696969696969697,
          "entries_filtered": 1511
        },
        {
          "coin": "SHIB",
          "pnl": 3.4826025410254005,
          "trades": 277,
          "wins": 106,
          "losses": 171,
          "flats": 0,
          "wr": 38.26714801444043,
          "pf": 0.6198830409356725,
          "entries_filtered": 1091
        },
        {
          "coin": "LINK",
          "pnl": 3.320393584480101,
          "trades": 156,
          "wins": 63,
          "losses": 92,
          "flats": 1,
          "wr": 40.38461538461539,
          "pf": 0.6847826086956521,
          "entries_filtered": 1285
        },
        {
          "coin": "ETH",
          "pnl": 0.3244872449234606,
          "trades": 36,
          "wins": 12,
          "losses": 24,
          "flats": 0,
          "wr": 33.33333333333333,
          "pf": 0.5,
          "entries_filtered": 1633
        },
        {
          "coin": "DOT",
          "pnl": 1.797686920506635,
          "trades": 123,
          "wins": 41,
          "losses": 82,
          "flats": 0,
          "wr": 33.33333333333333,
          "pf": 0.5,
          "entries_filtered": 1409
        },
        {
          "coin": "XRP",
          "pnl": 0.36159411486954696,
          "trades": 41,
          "wins": 15,
          "losses": 26,
          "flats": 0,
          "wr": 36.58536585365854,
          "pf": 0.576923076923077,
          "entries_filtered": 1668
        },
        {
          "coin": "ATOM",
          "pnl": 3.2403504804809984,
          "trades": 165,
          "wins": 65,
          "losses": 100,
          "flats": 0,
          "wr": 39.39393939393939,
          "pf": 0.65,
          "entries_filtered": 1301
        },
        {
          "coin": "SOL",
          "pnl": 1.0682983554425078,
          "trades": 31,
          "wins": 17,
          "losses": 14,
          "flats": 0,
          "wr": 54.83870967741935,
          "pf": 1.2142857142857142,
          "entries_filtered": 1674
        },
        {
          "coin": "DOGE",
          "pnl": -0.13617828689586986,
          "trades": 23,
          "wins": 5,
          "losses": 18,
          "flats": 0,
          "wr": 21.73913043478261,
          "pf": 0.2777777777777778,
          "entries_filtered": 1669
        },
        {
          "coin": "XLM",
          "pnl": 2.4616491726331873,
          "trades": 153,
          "wins": 57,
          "losses": 96,
          "flats": 0,
          "wr": 37.254901960784316,
          "pf": 0.59375,
          "entries_filtered": 1376
        },
        {
          "coin": "AVAX",
          "pnl": 3.800006113116723,
          "trades": 160,
          "wins": 72,
          "losses": 88,
          "flats": 0,
          "wr": 45.0,
          "pf": 0.8181818181818181,
          "entries_filtered": 1411
        },
        {
          "coin": "ALGO",
          "pnl": 4.712259188274857,
          "trades": 230,
          "wins": 87,
          "losses": 143,
          "flats": 0,
          "wr": 37.826086956521735,
          "pf": 0.6083916083916084,
          "entries_filtered": 1137
        },
        {
          "coin": "BNB",
          "pnl": 0.9059442545650427,
          "trades": 69,
          "wins": 32,
          "losses": 37,
          "flats": 0,
          "wr": 46.3768115942029,
          "pf": 0.8648648648648649,
          "entries_filtered": 1591
        },
        {
          "coin": "BTC",
          "pnl": 0.8232410933611192,
          "trades": 79,
          "wins": 38,
          "losses": 41,
          "flats": 0,
          "wr": 48.10126582278481,
          "pf": 0.9268292682926829,
          "entries_filtered": 1527
        }
      ],
      "entries_filtered_total": 26245,
      "filter_rate": 93.1631819956693
    },
    {
      "label": "P20_T5",
      "total_pnl": 36.060182966973656,
      "portfolio_wr": 39.80070339976554,
      "total_trades": 1706,
      "wins": 679,
      "losses": 1026,
      "flats": 1,
      "pf": 0.6617933723196882,
      "is_baseline": false,
      "coins": [
        {
          "coin": "DASH",
          "pnl": 3.5999525327355997,
          "trades": 62,
          "wins": 20,
          "losses": 42,
          "flats": 0,
          "wr": 32.25806451612903,
          "pf": 0.4761904761904761,
          "entries_filtered": 1558
        },
        {
          "coin": "UNI",
          "pnl": 3.4297481311734543,
          "trades": 67,
          "wins": 33,
          "losses": 34,
          "flats": 0,
          "wr": 49.25373134328358,
          "pf": 0.9705882352941176,
          "entries_filtered": 1488
        },
        {
          "coin": "NEAR",
          "pnl": 3.594797914882932,
          "trades": 111,
          "wins": 45,
          "losses": 66,
          "flats": 0,
          "wr": 40.54054054054054,
          "pf": 0.6818181818181819,
          "entries_filtered": 1399
        },
        {
          "coin": "ADA",
          "pnl": 0.9158080745515207,
          "trades": 48,
          "wins": 18,
          "losses": 30,
          "flats": 0,
          "wr": 37.5,
          "pf": 0.6,
          "entries_filtered": 1581
        },
        {
          "coin": "LTC",
          "pnl": 1.1330445695099627,
          "trades": 49,
          "wins": 22,
          "losses": 27,
          "flats": 0,
          "wr": 44.89795918367347,
          "pf": 0.8148148148148148,
          "entries_filtered": 1546
        },
        {
          "coin": "SHIB",
          "pnl": 3.2830958557161694,
          "trades": 256,
          "wins": 98,
          "losses": 158,
          "flats": 0,
          "wr": 38.28125,
          "pf": 0.620253164556962,
          "entries_filtered": 1141
        },
        {
          "coin": "LINK",
          "pnl": 3.2075875678950325,
          "trades": 141,
          "wins": 60,
          "losses": 80,
          "flats": 1,
          "wr": 42.5531914893617,
          "pf": 0.7500000000000001,
          "entries_filtered": 1328
        },
        {
          "coin": "ETH",
          "pnl": 0.2313374845121814,
          "trades": 25,
          "wins": 9,
          "losses": 16,
          "flats": 0,
          "wr": 36.0,
          "pf": 0.5625,
          "entries_filtered": 1656
        },
        {
          "coin": "DOT",
          "pnl": 1.5695330260597444,
          "trades": 112,
          "wins": 35,
          "losses": 77,
          "flats": 0,
          "wr": 31.25,
          "pf": 0.45454545454545453,
          "entries_filtered": 1434
        },
        {
          "coin": "XRP",
          "pnl": 0.285215301057832,
          "trades": 31,
          "wins": 14,
          "losses": 17,
          "flats": 0,
          "wr": 45.16129032258064,
          "pf": 0.823529411764706,
          "entries_filtered": 1691
        },
        {
          "coin": "ATOM",
          "pnl": 2.819393184061923,
          "trades": 156,
          "wins": 60,
          "losses": 96,
          "flats": 0,
          "wr": 38.46153846153847,
          "pf": 0.625,
          "entries_filtered": 1321
        },
        {
          "coin": "SOL",
          "pnl": 0.896187679573913,
          "trades": 26,
          "wins": 14,
          "losses": 12,
          "flats": 0,
          "wr": 53.84615384615385,
          "pf": 1.1666666666666667,
          "entries_filtered": 1681
        },
        {
          "coin": "DOGE",
          "pnl": -0.011370414991503708,
          "trades": 17,
          "wins": 4,
          "losses": 13,
          "flats": 0,
          "wr": 23.52941176470588,
          "pf": 0.3076923076923077,
          "entries_filtered": 1687
        },
        {
          "coin": "XLM",
          "pnl": 2.272802253383702,
          "trades": 139,
          "wins": 53,
          "losses": 86,
          "flats": 0,
          "wr": 38.1294964028777,
          "pf": 0.6162790697674418,
          "entries_filtered": 1410
        },
        {
          "coin": "AVAX",
          "pnl": 3.3035753411101467,
          "trades": 145,
          "wins": 64,
          "losses": 81,
          "flats": 0,
          "wr": 44.13793103448276,
          "pf": 0.7901234567901234,
          "entries_filtered": 1439
        },
        {
          "coin": "ALGO",
          "pnl": 4.2937505669355716,
          "trades": 220,
          "wins": 82,
          "losses": 138,
          "flats": 0,
          "wr": 37.27272727272727,
          "pf": 0.5942028985507246,
          "entries_filtered": 1163
        },
        {
          "coin": "BNB",
          "pnl": 0.6729231857092515,
          "trades": 38,
          "wins": 19,
          "losses": 19,
          "flats": 0,
          "wr": 50.0,
          "pf": 1.0,
          "entries_filtered": 1661
        },
        {
          "coin": "BTC",
          "pnl": 0.5628007130962231,
          "trades": 63,
          "wins": 29,
          "losses": 34,
          "flats": 0,
          "wr": 46.03174603174603,
          "pf": 0.8529411764705883,
          "entries_filtered": 1566
        }
      ],
      "entries_filtered_total": 26750,
      "filter_rate": 94.00477930840596
    },
    {
      "label": "P20_T10",
      "total_pnl": 35.81795424463142,
      "portfolio_wr": 39.52546296296296,
      "total_trades": 1728,
      "wins": 683,
      "losses": 1044,
      "flats": 1,
      "pf": 0.6542145593869731,
      "is_baseline": false,
      "coins": [
        {
          "coin": "DASH",
          "pnl": 3.5999525327355997,
          "trades": 62,
          "wins": 20,
          "losses": 42,
          "flats": 0,
          "wr": 32.25806451612903,
          "pf": 0.4761904761904761,
          "entries_filtered": 1558
        },
        {
          "coin": "UNI",
          "pnl": 3.4297481311734543,
          "trades": 67,
          "wins": 33,
          "losses": 34,
          "flats": 0,
          "wr": 49.25373134328358,
          "pf": 0.9705882352941176,
          "entries_filtered": 1488
        },
        {
          "coin": "NEAR",
          "pnl": 3.594797914882932,
          "trades": 111,
          "wins": 45,
          "losses": 66,
          "flats": 0,
          "wr": 40.54054054054054,
          "pf": 0.6818181818181819,
          "entries_filtered": 1399
        },
        {
          "coin": "ADA",
          "pnl": 0.9158080745515207,
          "trades": 48,
          "wins": 18,
          "losses": 30,
          "flats": 0,
          "wr": 37.5,
          "pf": 0.6,
          "entries_filtered": 1581
        },
        {
          "coin": "LTC",
          "pnl": 1.1330445695099627,
          "trades": 49,
          "wins": 22,
          "losses": 27,
          "flats": 0,
          "wr": 44.89795918367347,
          "pf": 0.8148148148148148,
          "entries_filtered": 1546
        },
        {
          "coin": "SHIB",
          "pnl": 3.2830958557161694,
          "trades": 256,
          "wins": 98,
          "losses": 158,
          "flats": 0,
          "wr": 38.28125,
          "pf": 0.620253164556962,
          "entries_filtered": 1141
        },
        {
          "coin": "LINK",
          "pnl": 3.2075875678950325,
          "trades": 141,
          "wins": 60,
          "losses": 80,
          "flats": 1,
          "wr": 42.5531914893617,
          "pf": 0.7500000000000001,
          "entries_filtered": 1328
        },
        {
          "coin": "ETH",
          "pnl": 0.15319340995873176,
          "trades": 28,
          "wins": 9,
          "losses": 19,
          "flats": 0,
          "wr": 32.142857142857146,
          "pf": 0.4736842105263158,
          "entries_filtered": 1648
        },
        {
          "coin": "DOT",
          "pnl": 1.5695330260597444,
          "trades": 112,
          "wins": 35,
          "losses": 77,
          "flats": 0,
          "wr": 31.25,
          "pf": 0.45454545454545453,
          "entries_filtered": 1434
        },
        {
          "coin": "XRP",
          "pnl": 0.255129736467552,
          "trades": 32,
          "wins": 14,
          "losses": 18,
          "flats": 0,
          "wr": 43.75,
          "pf": 0.7777777777777779,
          "entries_filtered": 1690
        },
        {
          "coin": "ATOM",
          "pnl": 2.819393184061923,
          "trades": 156,
          "wins": 60,
          "losses": 96,
          "flats": 0,
          "wr": 38.46153846153847,
          "pf": 0.625,
          "entries_filtered": 1321
        },
        {
          "coin": "SOL",
          "pnl": 0.896187679573913,
          "trades": 26,
          "wins": 14,
          "losses": 12,
          "flats": 0,
          "wr": 53.84615384615385,
          "pf": 1.1666666666666667,
          "entries_filtered": 1681
        },
        {
          "coin": "DOGE",
          "pnl": -0.011370414991503708,
          "trades": 17,
          "wins": 4,
          "losses": 13,
          "flats": 0,
          "wr": 23.52941176470588,
          "pf": 0.3076923076923077,
          "entries_filtered": 1687
        },
        {
          "coin": "XLM",
          "pnl": 2.272802253383702,
          "trades": 139,
          "wins": 53,
          "losses": 86,
          "flats": 0,
          "wr": 38.1294964028777,
          "pf": 0.6162790697674418,
          "entries_filtered": 1410
        },
        {
          "coin": "AVAX",
          "pnl": 3.3035753411101467,
          "trades": 145,
          "wins": 64,
          "losses": 81,
          "flats": 0,
          "wr": 44.13793103448276,
          "pf": 0.7901234567901234,
          "entries_filtered": 1439
        },
        {
          "coin": "ALGO",
          "pnl": 4.2937505669355716,
          "trades": 220,
          "wins": 82,
          "losses": 138,
          "flats": 0,
          "wr": 37.27272727272727,
          "pf": 0.5942028985507246,
          "entries_filtered": 1163
        },
        {
          "coin": "BNB",
          "pnl": 0.4697599798038965,
          "trades": 52,
          "wins": 21,
          "losses": 31,
          "flats": 0,
          "wr": 40.38461538461539,
          "pf": 0.6774193548387097,
          "entries_filtered": 1627
        },
        {
          "coin": "BTC",
          "pnl": 0.6319648358030747,
          "trades": 67,
          "wins": 31,
          "losses": 36,
          "flats": 0,
          "wr": 46.26865671641791,
          "pf": 0.8611111111111112,
          "entries_filtered": 1555
        }
      ],
      "entries_filtered_total": 26696,
      "filter_rate": 93.9206304531382
    },
    {
      "label": "P20_T20",
      "total_pnl": 37.817042350679216,
      "portfolio_wr": 39.69508752117448,
      "total_trades": 1771,
      "wins": 703,
      "losses": 1067,
      "flats": 1,
      "pf": 0.6588566073102156,
      "is_baseline": false,
      "coins": [
        {
          "coin": "DASH",
          "pnl": 4.83517119052506,
          "trades": 64,
          "wins": 21,
          "losses": 43,
          "flats": 0,
          "wr": 32.8125,
          "pf": 0.4883720930232558,
          "entries_filtered": 1555
        },
        {
          "coin": "UNI",
          "pnl": 3.4297481311734543,
          "trades": 67,
          "wins": 33,
          "losses": 34,
          "flats": 0,
          "wr": 49.25373134328358,
          "pf": 0.9705882352941176,
          "entries_filtered": 1488
        },
        {
          "coin": "NEAR",
          "pnl": 3.594797914882932,
          "trades": 111,
          "wins": 45,
          "losses": 66,
          "flats": 0,
          "wr": 40.54054054054054,
          "pf": 0.6818181818181819,
          "entries_filtered": 1399
        },
        {
          "coin": "ADA",
          "pnl": 0.9158080745515207,
          "trades": 48,
          "wins": 18,
          "losses": 30,
          "flats": 0,
          "wr": 37.5,
          "pf": 0.6,
          "entries_filtered": 1581
        },
        {
          "coin": "LTC",
          "pnl": 1.3486581670693027,
          "trades": 50,
          "wins": 23,
          "losses": 27,
          "flats": 0,
          "wr": 46.0,
          "pf": 0.8518518518518519,
          "entries_filtered": 1545
        },
        {
          "coin": "SHIB",
          "pnl": 3.2830958557161694,
          "trades": 256,
          "wins": 98,
          "losses": 158,
          "flats": 0,
          "wr": 38.28125,
          "pf": 0.620253164556962,
          "entries_filtered": 1141
        },
        {
          "coin": "LINK",
          "pnl": 3.2075875678950325,
          "trades": 141,
          "wins": 60,
          "losses": 80,
          "flats": 1,
          "wr": 42.5531914893617,
          "pf": 0.7500000000000001,
          "entries_filtered": 1328
        },
        {
          "coin": "ETH",
          "pnl": 0.5591929794508701,
          "trades": 35,
          "wins": 12,
          "losses": 23,
          "flats": 0,
          "wr": 34.285714285714285,
          "pf": 0.5217391304347826,
          "entries_filtered": 1636
        },
        {
          "coin": "DOT",
          "pnl": 1.5695330260597444,
          "trades": 112,
          "wins": 35,
          "losses": 77,
          "flats": 0,
          "wr": 31.25,
          "pf": 0.45454545454545453,
          "entries_filtered": 1434
        },
        {
          "coin": "XRP",
          "pnl": 0.014769916498039493,
          "trades": 40,
          "wins": 14,
          "losses": 26,
          "flats": 0,
          "wr": 35.0,
          "pf": 0.5384615384615385,
          "entries_filtered": 1674
        },
        {
          "coin": "ATOM",
          "pnl": 2.819393184061923,
          "trades": 156,
          "wins": 60,
          "losses": 96,
          "flats": 0,
          "wr": 38.46153846153847,
          "pf": 0.625,
          "entries_filtered": 1321
        },
        {
          "coin": "SOL",
          "pnl": 0.8659188232700075,
          "trades": 27,
          "wins": 14,
          "losses": 13,
          "flats": 0,
          "wr": 51.85185185185185,
          "pf": 1.076923076923077,
          "entries_filtered": 1680
        },
        {
          "coin": "DOGE",
          "pnl": -0.011370414991503708,
          "trades": 17,
          "wins": 4,
          "losses": 13,
          "flats": 0,
          "wr": 23.52941176470588,
          "pf": 0.3076923076923077,
          "entries_filtered": 1687
        },
        {
          "coin": "XLM",
          "pnl": 2.272802253383702,
          "trades": 139,
          "wins": 53,
          "losses": 86,
          "flats": 0,
          "wr": 38.1294964028777,
          "pf": 0.6162790697674418,
          "entries_filtered": 1410
        },
        {
          "coin": "AVAX",
          "pnl": 3.3035753411101467,
          "trades": 145,
          "wins": 64,
          "losses": 81,
          "flats": 0,
          "wr": 44.13793103448276,
          "pf": 0.7901234567901234,
          "entries_filtered": 1439
        },
        {
          "coin": "ALGO",
          "pnl": 4.2937505669355716,
          "trades": 220,
          "wins": 82,
          "losses": 138,
          "flats": 0,
          "wr": 37.27272727272727,
          "pf": 0.5942028985507246,
          "entries_filtered": 1163
        },
        {
          "coin": "BNB",
          "pnl": 0.7986255973336824,
          "trades": 70,
          "wins": 33,
          "losses": 37,
          "flats": 0,
          "wr": 47.14285714285714,
          "pf": 0.8918918918918919,
          "entries_filtered": 1589
        },
        {
          "coin": "BTC",
          "pnl": 0.7159841757535617,
          "trades": 73,
          "wins": 34,
          "losses": 39,
          "flats": 0,
          "wr": 46.57534246575342,
          "pf": 0.8717948717948718,
          "entries_filtered": 1539
        }
      ],
      "entries_filtered_total": 26609,
      "filter_rate": 93.75968992248062
    },
    {
      "label": "P30_T5",
      "total_pnl": 28.368224564929378,
      "portfolio_wr": 38.648860958366065,
      "total_trades": 1273,
      "wins": 492,
      "losses": 781,
      "flats": 0,
      "pf": 0.6299615877080667,
      "is_baseline": false,
      "coins": [
        {
          "coin": "DASH",
          "pnl": 2.5732400471397483,
          "trades": 43,
          "wins": 13,
          "losses": 30,
          "flats": 0,
          "wr": 30.23255813953488,
          "pf": 0.4333333333333333,
          "entries_filtered": 1600
        },
        {
          "coin": "UNI",
          "pnl": 2.860561349569764,
          "trades": 48,
          "wins": 25,
          "losses": 23,
          "flats": 0,
          "wr": 52.083333333333336,
          "pf": 1.0869565217391304,
          "entries_filtered": 1532
        },
        {
          "coin": "NEAR",
          "pnl": 2.781537131261871,
          "trades": 78,
          "wins": 30,
          "losses": 48,
          "flats": 0,
          "wr": 38.46153846153847,
          "pf": 0.625,
          "entries_filtered": 1471
        },
        {
          "coin": "ADA",
          "pnl": 0.5802492533725427,
          "trades": 35,
          "wins": 11,
          "losses": 24,
          "flats": 0,
          "wr": 31.428571428571427,
          "pf": 0.45833333333333337,
          "entries_filtered": 1607
        },
        {
          "coin": "LTC",
          "pnl": 1.2967645495421039,
          "trades": 36,
          "wins": 19,
          "losses": 17,
          "flats": 0,
          "wr": 52.77777777777778,
          "pf": 1.1176470588235294,
          "entries_filtered": 1577
        },
        {
          "coin": "SHIB",
          "pnl": 2.3230946965199024,
          "trades": 200,
          "wins": 74,
          "losses": 126,
          "flats": 0,
          "wr": 37.0,
          "pf": 0.5873015873015873,
          "entries_filtered": 1265
        },
        {
          "coin": "LINK",
          "pnl": 2.2511114953748574,
          "trades": 96,
          "wins": 38,
          "losses": 58,
          "flats": 0,
          "wr": 39.58333333333333,
          "pf": 0.6551724137931034,
          "entries_filtered": 1425
        },
        {
          "coin": "ETH",
          "pnl": 0.211858020622941,
          "trades": 19,
          "wins": 6,
          "losses": 13,
          "flats": 0,
          "wr": 31.57894736842105,
          "pf": 0.46153846153846156,
          "entries_filtered": 1670
        },
        {
          "coin": "DOT",
          "pnl": 1.8552705334492003,
          "trades": 91,
          "wins": 32,
          "losses": 59,
          "flats": 0,
          "wr": 35.16483516483517,
          "pf": 0.5423728813559322,
          "entries_filtered": 1488
        },
        {
          "coin": "XRP",
          "pnl": -0.007849576939150893,
          "trades": 22,
          "wins": 7,
          "losses": 15,
          "flats": 0,
          "wr": 31.818181818181817,
          "pf": 0.4666666666666667,
          "entries_filtered": 1709
        },
        {
          "coin": "ATOM",
          "pnl": 2.2350635768420375,
          "trades": 120,
          "wins": 45,
          "losses": 75,
          "flats": 0,
          "wr": 37.5,
          "pf": 0.6,
          "entries_filtered": 1402
        },
        {
          "coin": "SOL",
          "pnl": 0.8578776666317935,
          "trades": 20,
          "wins": 11,
          "losses": 9,
          "flats": 0,
          "wr": 55.00000000000001,
          "pf": 1.2222222222222223,
          "entries_filtered": 1695
        },
        {
          "coin": "DOGE",
          "pnl": 0.02427647975858349,
          "trades": 10,
          "wins": 3,
          "losses": 7,
          "flats": 0,
          "wr": 30.0,
          "pf": 0.42857142857142855,
          "entries_filtered": 1704
        },
        {
          "coin": "XLM",
          "pnl": 1.7309622033831573,
          "trades": 111,
          "wins": 40,
          "losses": 71,
          "flats": 0,
          "wr": 36.03603603603604,
          "pf": 0.5633802816901408,
          "entries_filtered": 1469
        },
        {
          "coin": "AVAX",
          "pnl": 2.6019994213824162,
          "trades": 109,
          "wins": 47,
          "losses": 62,
          "flats": 0,
          "wr": 43.11926605504588,
          "pf": 0.7580645161290323,
          "entries_filtered": 1520
        },
        {
          "coin": "ALGO",
          "pnl": 3.175742235034548,
          "trades": 158,
          "wins": 55,
          "losses": 103,
          "flats": 0,
          "wr": 34.810126582278485,
          "pf": 0.5339805825242718,
          "entries_filtered": 1297
        },
        {
          "coin": "BNB",
          "pnl": 0.6675687913390078,
          "trades": 31,
          "wins": 16,
          "losses": 15,
          "flats": 0,
          "wr": 51.61290322580645,
          "pf": 1.0666666666666667,
          "entries_filtered": 1677
        },
        {
          "coin": "BTC",
          "pnl": 0.3488966906440538,
          "trades": 46,
          "wins": 20,
          "losses": 26,
          "flats": 0,
          "wr": 43.47826086956522,
          "pf": 0.7692307692307692,
          "entries_filtered": 1602
        }
      ],
      "entries_filtered_total": 27710,
      "filter_rate": 95.60777007211124
    },
    {
      "label": "P30_T10",
      "total_pnl": 28.386783462803834,
      "portfolio_wr": 38.473400154202004,
      "total_trades": 1297,
      "wins": 499,
      "losses": 798,
      "flats": 0,
      "pf": 0.62531328320802,
      "is_baseline": false,
      "coins": [
        {
          "coin": "DASH",
          "pnl": 2.5732400471397483,
          "trades": 43,
          "wins": 13,
          "losses": 30,
          "flats": 0,
          "wr": 30.23255813953488,
          "pf": 0.4333333333333333,
          "entries_filtered": 1600
        },
        {
          "coin": "UNI",
          "pnl": 2.860561349569764,
          "trades": 48,
          "wins": 25,
          "losses": 23,
          "flats": 0,
          "wr": 52.083333333333336,
          "pf": 1.0869565217391304,
          "entries_filtered": 1532
        },
        {
          "coin": "NEAR",
          "pnl": 2.781537131261871,
          "trades": 78,
          "wins": 30,
          "losses": 48,
          "flats": 0,
          "wr": 38.46153846153847,
          "pf": 0.625,
          "entries_filtered": 1471
        },
        {
          "coin": "ADA",
          "pnl": 0.5802492533725427,
          "trades": 35,
          "wins": 11,
          "losses": 24,
          "flats": 0,
          "wr": 31.428571428571427,
          "pf": 0.45833333333333337,
          "entries_filtered": 1607
        },
        {
          "coin": "LTC",
          "pnl": 1.2967645495421039,
          "trades": 36,
          "wins": 19,
          "losses": 17,
          "flats": 0,
          "wr": 52.77777777777778,
          "pf": 1.1176470588235294,
          "entries_filtered": 1577
        },
        {
          "coin": "SHIB",
          "pnl": 2.3230946965199024,
          "trades": 200,
          "wins": 74,
          "losses": 126,
          "flats": 0,
          "wr": 37.0,
          "pf": 0.5873015873015873,
          "entries_filtered": 1265
        },
        {
          "coin": "LINK",
          "pnl": 2.2511114953748574,
          "trades": 96,
          "wins": 38,
          "losses": 58,
          "flats": 0,
          "wr": 39.58333333333333,
          "pf": 0.6551724137931034,
          "entries_filtered": 1425
        },
        {
          "coin": "ETH",
          "pnl": 0.15630210110818155,
          "trades": 22,
          "wins": 7,
          "losses": 15,
          "flats": 0,
          "wr": 31.818181818181817,
          "pf": 0.4666666666666667,
          "entries_filtered": 1664
        },
        {
          "coin": "DOT",
          "pnl": 1.8552705334492003,
          "trades": 91,
          "wins": 32,
          "losses": 59,
          "flats": 0,
          "wr": 35.16483516483517,
          "pf": 0.5423728813559322,
          "entries_filtered": 1488
        },
        {
          "coin": "XRP",
          "pnl": 0.1350645750676165,
          "trades": 26,
          "wins": 8,
          "losses": 18,
          "flats": 0,
          "wr": 30.76923076923077,
          "pf": 0.4444444444444445,
          "entries_filtered": 1702
        },
        {
          "coin": "ATOM",
          "pnl": 2.2350635768420375,
          "trades": 120,
          "wins": 45,
          "losses": 75,
          "flats": 0,
          "wr": 37.5,
          "pf": 0.6,
          "entries_filtered": 1402
        },
        {
          "coin": "SOL",
          "pnl": 0.82762030333177,
          "trades": 21,
          "wins": 11,
          "losses": 10,
          "flats": 0,
          "wr": 52.38095238095239,
          "pf": 1.1,
          "entries_filtered": 1694
        },
        {
          "coin": "DOGE",
          "pnl": 0.02427647975858349,
          "trades": 10,
          "wins": 3,
          "losses": 7,
          "flats": 0,
          "wr": 30.0,
          "pf": 0.42857142857142855,
          "entries_filtered": 1704
        },
        {
          "coin": "XLM",
          "pnl": 1.7309622033831573,
          "trades": 111,
          "wins": 40,
          "losses": 71,
          "flats": 0,
          "wr": 36.03603603603604,
          "pf": 0.5633802816901408,
          "entries_filtered": 1469
        },
        {
          "coin": "AVAX",
          "pnl": 2.6019994213824162,
          "trades": 109,
          "wins": 47,
          "losses": 62,
          "flats": 0,
          "wr": 43.11926605504588,
          "pf": 0.7580645161290323,
          "entries_filtered": 1520
        },
        {
          "coin": "ALGO",
          "pnl": 3.175742235034548,
          "trades": 158,
          "wins": 55,
          "losses": 103,
          "flats": 0,
          "wr": 34.810126582278485,
          "pf": 0.5339805825242718,
          "entries_filtered": 1297
        },
        {
          "coin": "BNB",
          "pnl": 0.5298753997471977,
          "trades": 44,
          "wins": 19,
          "losses": 25,
          "flats": 0,
          "wr": 43.18181818181818,
          "pf": 0.76,
          "entries_filtered": 1648
        },
        {
          "coin": "BTC",
          "pnl": 0.44804811091833585,
          "trades": 49,
          "wins": 22,
          "losses": 27,
          "flats": 0,
          "wr": 44.89795918367347,
          "pf": 0.8148148148148148,
          "entries_filtered": 1595
        }
      ],
      "entries_filtered_total": 27660,
      "filter_rate": 95.52094484925925
    },
    {
      "label": "P30_T20",
      "total_pnl": 29.01793151264411,
      "portfolio_wr": 38.43843843843844,
      "total_trades": 1332,
      "wins": 512,
      "losses": 820,
      "flats": 0,
      "pf": 0.624390243902439,
      "is_baseline": false,
      "coins": [
        {
          "coin": "DASH",
          "pnl": 2.5732400471397483,
          "trades": 43,
          "wins": 13,
          "losses": 30,
          "flats": 0,
          "wr": 30.23255813953488,
          "pf": 0.4333333333333333,
          "entries_filtered": 1600
        },
        {
          "coin": "UNI",
          "pnl": 2.8297031811648736,
          "trades": 49,
          "wins": 25,
          "losses": 24,
          "flats": 0,
          "wr": 51.02040816326531,
          "pf": 1.0416666666666667,
          "entries_filtered": 1531
        },
        {
          "coin": "NEAR",
          "pnl": 2.781537131261871,
          "trades": 78,
          "wins": 30,
          "losses": 48,
          "flats": 0,
          "wr": 38.46153846153847,
          "pf": 0.625,
          "entries_filtered": 1471
        },
        {
          "coin": "ADA",
          "pnl": 0.5802492533725427,
          "trades": 35,
          "wins": 11,
          "losses": 24,
          "flats": 0,
          "wr": 31.428571428571427,
          "pf": 0.45833333333333337,
          "entries_filtered": 1607
        },
        {
          "coin": "LTC",
          "pnl": 1.5127271947746692,
          "trades": 37,
          "wins": 20,
          "losses": 17,
          "flats": 0,
          "wr": 54.054054054054056,
          "pf": 1.1764705882352942,
          "entries_filtered": 1576
        },
        {
          "coin": "SHIB",
          "pnl": 2.3230946965199024,
          "trades": 200,
          "wins": 74,
          "losses": 126,
          "flats": 0,
          "wr": 37.0,
          "pf": 0.5873015873015873,
          "entries_filtered": 1265
        },
        {
          "coin": "LINK",
          "pnl": 2.2511114953748574,
          "trades": 96,
          "wins": 38,
          "losses": 58,
          "flats": 0,
          "wr": 39.58333333333333,
          "pf": 0.6551724137931034,
          "entries_filtered": 1425
        },
        {
          "coin": "ETH",
          "pnl": 0.4979768660107453,
          "trades": 27,
          "wins": 9,
          "losses": 18,
          "flats": 0,
          "wr": 33.33333333333333,
          "pf": 0.5,
          "entries_filtered": 1653
        },
        {
          "coin": "DOT",
          "pnl": 1.8552705334492003,
          "trades": 91,
          "wins": 32,
          "losses": 59,
          "flats": 0,
          "wr": 35.16483516483517,
          "pf": 0.5423728813559322,
          "entries_filtered": 1488
        },
        {
          "coin": "XRP",
          "pnl": 0.021455542875841616,
          "trades": 34,
          "wins": 9,
          "losses": 25,
          "flats": 0,
          "wr": 26.47058823529412,
          "pf": 0.36,
          "entries_filtered": 1684
        },
        {
          "coin": "ATOM",
          "pnl": 2.2350635768420375,
          "trades": 120,
          "wins": 45,
          "losses": 75,
          "flats": 0,
          "wr": 37.5,
          "pf": 0.6,
          "entries_filtered": 1402
        },
        {
          "coin": "SOL",
          "pnl": 0.82762030333177,
          "trades": 21,
          "wins": 11,
          "losses": 10,
          "flats": 0,
          "wr": 52.38095238095239,
          "pf": 1.1,
          "entries_filtered": 1694
        },
        {
          "coin": "DOGE",
          "pnl": 0.02427647975858349,
          "trades": 10,
          "wins": 3,
          "losses": 7,
          "flats": 0,
          "wr": 30.0,
          "pf": 0.42857142857142855,
          "entries_filtered": 1704
        },
        {
          "coin": "XLM",
          "pnl": 1.7004429147221458,
          "trades": 112,
          "wins": 40,
          "losses": 72,
          "flats": 0,
          "wr": 35.714285714285715,
          "pf": 0.5555555555555556,
          "entries_filtered": 1468
        },
        {
          "coin": "AVAX",
          "pnl": 2.6019994213824162,
          "trades": 109,
          "wins": 47,
          "losses": 62,
          "flats": 0,
          "wr": 43.11926605504588,
          "pf": 0.7580645161290323,
          "entries_filtered": 1520
        },
        {
          "coin": "ALGO",
          "pnl": 3.175742235034548,
          "trades": 158,
          "wins": 55,
          "losses": 103,
          "flats": 0,
          "wr": 34.810126582278485,
          "pf": 0.5339805825242718,
          "entries_filtered": 1297
        },
        {
          "coin": "BNB",
          "pnl": 0.6835353157026276,
          "trades": 57,
          "wins": 25,
          "losses": 32,
          "flats": 0,
          "wr": 43.859649122807014,
          "pf": 0.78125,
          "entries_filtered": 1621
        },
        {
          "coin": "BTC",
          "pnl": 0.5428853239257307,
          "trades": 55,
          "wins": 25,
          "losses": 30,
          "flats": 0,
          "wr": 45.45454545454545,
          "pf": 0.8333333333333333,
          "entries_filtered": 1578
        }
      ],
      "entries_filtered_total": 27584,
      "filter_rate": 95.39355374187302
    }
  ]
}